mt5_conn/Account.py
mt5_conn/MT5app.py
mt5_conn/Price.py
mt5_conn/__init__.py
mt5_conn/mt5_objects.py
MetaTrader5_python_connector-0.0.1.dist-info/LICENSE
MetaTrader5_python_connector-0.0.1.dist-info/METADATA
MetaTrader5_python_connector-0.0.1.dist-info/WHEEL
MetaTrader5_python_connector-0.0.1.dist-info/top_level.txt
MetaTrader5_python_connector-0.0.1.dist-info/RECORD
