Metadata-Version: 2.1
Name: MetaTrader5-python-connector
Version: 0.0.1
Summary: A package for interacting and retrieving data from the
Home-page: UNKNOWN
Author: Dag Arne Lydvo
Author-email: daglyd@outlook.com
License: UNKNOWN
Platform: UNKNOWN
